bird_identifier/__init__.py
bird_identifier-0.1.0.dist-info/LICENSE
bird_identifier-0.1.0.dist-info/METADATA
bird_identifier-0.1.0.dist-info/WHEEL
bird_identifier-0.1.0.dist-info/RECORD
